ojin/__init__.py
ojin/cacert.pem
ojin/ojin_client.py
ojin/ojin_client_messages.py
ojin/profiling_utils.py
ojin/entities/interaction_messages.py
ojin/entities/session_messages.py
ojin_client-0.6.3.dist-info/METADATA
ojin_client-0.6.3.dist-info/WHEEL
ojin_client-0.6.3.dist-info/top_level.txt
ojin_client-0.6.3.dist-info/RECORD
