Metadata-Version: 2.4
Name: ojin-client
Version: 0.6.3
Summary: Ojin platform services
Author: Journee
License: Apache-2.0
Project-URL: Homepage, https://github.com/journee-live/ojin
Classifier: License :: OSI Approved :: Apache Software License
Requires-Python: >=3.10
Requires-Dist: websockets==13.1
Requires-Dist: async-lru>=2.0.5
Requires-Dist: pyjwt>=2.10.1
Requires-Dist: pydantic-settings>=2.8.1
Requires-Dist: deprecated
Provides-Extra: dev
Requires-Dist: pytest>=8.3.5; extra == "dev"
Requires-Dist: pytest-asyncio>=0.26.0; extra == "dev"
Requires-Dist: pytest-cov>=4.1.0; extra == "dev"
Requires-Dist: pytest-httpx>=0.35.0; extra == "dev"
Requires-Dist: ruff>=0.11.4; extra == "dev"
Requires-Dist: build>=0.10.0; extra == "dev"
Requires-Dist: twine>=5.0.0; extra == "dev"
Requires-Dist: fastapi>=0.115.13; extra == "dev"
Requires-Dist: uvicorn>=0.34.3; extra == "dev"
